pytest_pytestrail/__init__.py
pytest_pytestrail/__version__.py
pytest_pytestrail/_case.py
pytest_pytestrail/_config.py
pytest_pytestrail/_constants.py
pytest_pytestrail/_sender.py
pytest_pytestrail/plugin.py
pytest_pytestrail/pytestrail.py
pytest_pytestrail-0.10.5.dist-info/LICENSE
pytest_pytestrail-0.10.5.dist-info/METADATA
pytest_pytestrail-0.10.5.dist-info/WHEEL
pytest_pytestrail-0.10.5.dist-info/entry_points.txt
pytest_pytestrail-0.10.5.dist-info/top_level.txt
pytest_pytestrail-0.10.5.dist-info/RECORD
