Metadata-Version: 2.1
Name: pytest-pytestrail
Version: 0.10.5
Summary: Pytest plugin for interaction with TestRail
Home-page: https://github.com/tolstislon/pytest-pytestrail
Author: tolstislon
Author-email: tolstislon@gmail.com
License: MIT License
Keywords: testrail,pytest,pytest-testrail,pytest-pytestrail,testrail_api,api
Platform: UNKNOWN
Classifier: Development Status :: 4 - Beta
Classifier: Intended Audience :: Developers
Classifier: License :: OSI Approved :: MIT License
Classifier: Operating System :: OS Independent
Classifier: Framework :: Pytest
Classifier: Environment :: Plugins
Classifier: Programming Language :: Python :: 3.5
Classifier: Programming Language :: Python :: 3.6
Classifier: Programming Language :: Python :: 3.7
Classifier: Programming Language :: Python :: 3.8
Classifier: Programming Language :: Python :: 3.9
Classifier: Programming Language :: Python :: Implementation
Classifier: Programming Language :: Python :: Implementation :: CPython
Classifier: Programming Language :: Python :: Implementation :: PyPy
Classifier: Topic :: Software Development :: Testing
Classifier: Topic :: Software Development :: Quality Assurance
Requires-Python: >=3.5
Requires-Dist: pytest (>=3.8.0)
Requires-Dist: testrail-api (>=1.8.0)
